[{
  "type": "flex",
  "altText": "You received a message",
  "contents": {
  "type": "bubble",
  "hero": {
    "type": "image",
    "url": "https://sv1.picz.in.th/images/2021/08/13/2uB4Iq.gif",
    "size": "full",
    "aspectRatio": "1:1",
    "aspectMode": "cover",
    "action": {
      "type": "uri",
      "uri": "http://ufa-bet191.com/"
    },
    "animated": true
  },
  "body": {
    "type": "box",
    "layout": "vertical",
    "contents": [
      {
        "type": "text",
        "text": "AUTOBET",
        "align": "center",
        "weight": "bold",
        "color": "#FF00CC"
      },
      {
        "type": "text",
        "text": "ระบบฝากถอนอัตโนมัติ รวดเร็วภายใน 3 วิ สมัครสมาชิกใหม่ รับโบนัส 100%",
        "weight": "bold",
        "wrap": true,
        "align": "center",
        "margin": "none",
        "size": "sm",
        "color": "#A020F0"
      }
    ]
  },
  "footer": {
    "type": "box",
    "layout": "horizontal",
    "spacing": "sm",
    "contents": [
      {
        "type": "button",
        "style": "primary",
        "height": "sm",
        "action": {
          "type": "uri",
          "label": "สมัครรับโบนัส",
          "uri": "http://ufa-bet191.com/"
        },
        "color": "#FF66FF"
      },
      {
        "type": "button",
        "style": "primary",
        "height": "sm",
        "action": {
          "type": "uri",
          "label": "เเชร์เลย",
          "uri": "https://liff.line.me/1656317102-Ze2nDd8r?content=https://boss12123.github.io/jk898.json"
        },
        "color": "#CC99FF"
      },
      {
        "type": "spacer",
        "size": "sm"
      }
    ],
    "flex": 0
  }
}
}]
